[
  {
    "fact": "Mentioned on 2026-02-01",
    "category": "context",
    "timestamp": "2026-02-01",
    "source": "memory/2026-02-01.md",
    "status": "active",
    "supersededBy": null,
    "relatedEntities": [],
    "id": "rachel-kim-1769990901596-0",
    "lastAccessed": "2026-02-02T00:08:21.596Z",
    "accessCount": 0
  },
  {
    "fact": "infra, two-week Twilio webho...",
    "category": "context",
    "timestamp": "2026-02-01",
    "source": "memory/2026-02-01.md",
    "status": "active",
    "supersededBy": null,
    "relatedEntities": [],
    "id": "rachel-kim-1769991487898",
    "lastAccessed": "2026-02-02T00:18:07.898Z",
    "accessCount": 0
  },
  {
    "fact": "Worked on webho...",
    "category": "context",
    "timestamp": "2026-02-01",
    "source": "memory/2026-02-01.md",
    "status": "active",
    "supersededBy": null,
    "relatedEntities": [],
    "id": "rachel-kim-1769993916212",
    "lastAccessed": "2026-02-02T00:58:36.212Z",
    "accessCount": 0
  },
  {
    "fact": "Infra",
    "category": "context",
    "timestamp": "2026-02-01",
    "source": "memory/2026-02-01.md",
    "status": "active",
    "supersededBy": null,
    "relatedEntities": [],
    "id": "rachel-kim-1769996021917",
    "lastAccessed": "2026-02-02T01:33:41.917Z",
    "accessCount": 0
  },
  {
    "fact": "two-week Twilio webho...",
    "category": "context",
    "timestamp": "2026-02-01",
    "source": "memory/2026-02-01.md",
    "status": "active",
    "supersededBy": null,
    "relatedEntities": [],
    "id": "rachel-kim-1769996021918",
    "lastAccessed": "2026-02-02T01:33:41.918Z",
    "accessCount": 0
  },
  {
    "fact": "Worked on webho... for Twilio",
    "category": "context",
    "timestamp": "2026-02-01",
    "source": "memory/2026-02-01.md",
    "status": "active",
    "supersededBy": null,
    "relatedEntities": [],
    "id": "rachel-kim-1769996382514",
    "lastAccessed": "2026-02-02T01:39:42.514Z",
    "accessCount": 0
  },
  {
    "fact": "Infra work for Project Atlas",
    "category": "context",
    "timestamp": "2026-02-01",
    "source": "memory/2026-02-01.md",
    "status": "active",
    "supersededBy": null,
    "relatedEntities": [],
    "id": "rachel-kim-1769996382527",
    "lastAccessed": "2026-02-02T01:39:42.527Z",
    "accessCount": 0
  },
  {
    "fact": "Working on Twilio webho...",
    "category": "context",
    "timestamp": "2026-02-01",
    "source": "memory/2026-02-01.md",
    "status": "active",
    "supersededBy": null,
    "relatedEntities": [],
    "id": "rachel-kim-1770060486468",
    "lastAccessed": "2026-02-02T19:28:06.468Z",
    "accessCount": 0
  }
]