[
  {
    "fact": "Role: lead engineer",
    "category": "context",
    "timestamp": "2026-02-01",
    "source": "memory/2026-02-01.md",
    "status": "active",
    "supersededBy": null,
    "relatedEntities": [],
    "id": "sarah-chen-1769989834253-0",
    "lastAccessed": "2026-02-03T01:44:57.418Z",
    "accessCount": 1,
    "tier": "hot"
  },
  {
    "fact": "Mentioned on 2026-02-01",
    "category": "context",
    "timestamp": "2026-02-01",
    "source": "memory/2026-02-01.md",
    "status": "active",
    "supersededBy": null,
    "relatedEntities": [],
    "id": "sarah-chen-1769990901593",
    "lastAccessed": "2026-02-03T01:44:57.418Z",
    "accessCount": 1
  },
  {
    "fact": "lead engineer, Austin / bi-weekly SF flights",
    "category": "context",
    "timestamp": "2026-02-01",
    "source": "memory/2026-02-01.md",
    "status": "active",
    "supersededBy": null,
    "relatedEntities": [],
    "id": "sarah-chen-1769991487899",
    "lastAccessed": "2026-02-03T01:44:57.418Z",
    "accessCount": 1
  },
  {
    "fact": "Lead engineer",
    "category": "context",
    "timestamp": "2026-02-01",
    "source": "memory/2026-02-01.md",
    "status": "active",
    "supersededBy": null,
    "relatedEntities": [],
    "id": "sarah-chen-1769993916212",
    "lastAccessed": "2026-02-03T01:44:57.418Z",
    "accessCount": 1
  },
  {
    "fact": "Austin / bi-weekly SF flights",
    "category": "context",
    "timestamp": "2026-02-01",
    "source": "memory/2026-02-01.md",
    "status": "active",
    "supersededBy": null,
    "relatedEntities": [],
    "id": "sarah-chen-1769993916213",
    "lastAccessed": "2026-02-03T01:44:57.418Z",
    "accessCount": 1
  },
  {
    "fact": "Lead engineer at Meridian Labs",
    "category": "context",
    "timestamp": "2026-02-01",
    "source": "memory/2026-02-01.md",
    "status": "active",
    "supersededBy": null,
    "relatedEntities": [],
    "id": "sarah-chen-1769996382515",
    "lastAccessed": "2026-02-03T01:44:57.418Z",
    "accessCount": 1
  },
  {
    "fact": "working out of Austin office",
    "category": "context",
    "timestamp": "2026-02-01",
    "source": "memory/2026-02-01.md",
    "status": "active",
    "supersededBy": null,
    "relatedEntities": [],
    "id": "sarah-chen-1769996382516",
    "lastAccessed": "2026-02-03T01:44:57.418Z",
    "accessCount": 1
  },
  {
    "fact": "Lead engineer at Meridian Labs, Austin / bi-weekly SF flights",
    "category": "context",
    "timestamp": "2026-02-01",
    "source": "memory/2026-02-01.md",
    "status": "active",
    "supersededBy": null,
    "relatedEntities": [],
    "id": "sarah-chen-1769997700442",
    "lastAccessed": "2026-02-03T01:44:57.418Z",
    "accessCount": 1
  },
  {
    "fact": "works from Austin and San Francisco",
    "category": "context",
    "timestamp": "2026-02-01",
    "source": "memory/2026-02-01.md",
    "status": "active",
    "supersededBy": null,
    "relatedEntities": [],
    "id": "sarah-chen-1770060256242",
    "lastAccessed": "2026-02-03T01:44:57.418Z",
    "accessCount": 1
  },
  {
    "fact": "Lead engineer of Project Atlas",
    "category": "context",
    "timestamp": "2026-02-01",
    "source": "memory/2026-02-01.md",
    "status": "active",
    "supersededBy": null,
    "relatedEntities": [],
    "id": "sarah-chen-1770060422034",
    "lastAccessed": "2026-02-03T01:44:57.418Z",
    "accessCount": 1
  },
  {
    "fact": "Lead engineer at Meridian Labs, works out of Austin office",
    "category": "context",
    "timestamp": "2026-02-01",
    "source": "memory/2026-02-01.md",
    "status": "active",
    "supersededBy": null,
    "relatedEntities": [],
    "id": "sarah-chen-1770083119279",
    "lastAccessed": "2026-02-03T01:45:19.279Z",
    "accessCount": 0
  },
  {
    "fact": "works out of Austin office",
    "category": "context",
    "timestamp": "2026-02-01",
    "source": "memory/2026-02-01.md",
    "status": "active",
    "supersededBy": null,
    "relatedEntities": [],
    "id": "sarah-chen-1770084019653",
    "lastAccessed": "2026-02-03T02:00:19.653Z",
    "accessCount": 0
  },
  {
    "fact": "Lead engineer of Project Atlas, works from Austin and San Francisco",
    "category": "context",
    "timestamp": "2026-02-01",
    "source": "memory/2026-02-01.md",
    "status": "active",
    "supersededBy": null,
    "relatedEntities": [],
    "id": "sarah-chen-1770089418460",
    "lastAccessed": "2026-02-03T03:30:18.460Z",
    "accessCount": 0
  },
  {
    "fact": "Lead engineer of Project Atlas, works out of Austin office",
    "category": "context",
    "timestamp": "2026-02-01",
    "source": "memory/2026-02-01.md",
    "status": "active",
    "supersededBy": null,
    "relatedEntities": [],
    "id": "sarah-chen-1770098422930",
    "lastAccessed": "2026-02-03T06:00:22.930Z",
    "accessCount": 0
  },
  {
    "fact": "Lead engineer at Meridian Labs, working out of Austin office",
    "category": "context",
    "timestamp": "2026-02-01",
    "source": "memory/2026-02-01.md",
    "status": "active",
    "supersededBy": null,
    "relatedEntities": [],
    "id": "sarah-chen-1770102930762",
    "lastAccessed": "2026-02-03T07:15:30.762Z",
    "accessCount": 0
  },
  {
    "fact": "Lead engineer of Project Atlas, working out of Austin office",
    "category": "context",
    "timestamp": "2026-02-01",
    "source": "memory/2026-02-01.md",
    "status": "active",
    "supersededBy": null,
    "relatedEntities": [],
    "id": "sarah-chen-1770106527740",
    "lastAccessed": "2026-02-03T08:15:27.740Z",
    "accessCount": 0
  },
  {
    "fact": "Lead engineer at Meridian Labs, works from Austin and San Francisco",
    "category": "context",
    "timestamp": "2026-02-01",
    "source": "memory/2026-02-01.md",
    "status": "active",
    "supersededBy": null,
    "relatedEntities": [],
    "id": "sarah-chen-1770111024476",
    "lastAccessed": "2026-02-03T09:30:24.476Z",
    "accessCount": 0
  },
  {
    "fact": "has been driving the core API redesign alongside Marcus Webb",
    "category": "context",
    "timestamp": "2026-02-01",
    "source": "memory/2026-02-01.md",
    "status": "active",
    "supersededBy": null,
    "relatedEntities": [],
    "id": "sarah-chen-1770112820614",
    "lastAccessed": "2026-02-03T10:00:20.614Z",
    "accessCount": 0
  },
  {
    "fact": "Project Atlas",
    "category": "context",
    "timestamp": "2026-02-01",
    "source": "memory/2026-02-01.md",
    "status": "active",
    "supersededBy": null,
    "relatedEntities": [],
    "id": "sarah-chen-1770129925120",
    "lastAccessed": "2026-02-03T14:45:25.120Z",
    "accessCount": 0
  }
]